fcat/__init__.py
fcat/annoToolsFcat.txt
fcat/assessCompleteness.py
fcat/calcCutoff.py
fcat/createPhyloprofile.py
fcat/fcat.py
fcat/functions.py
fcat/mergePhyloprofile.py
fcat/searchOrtho.py
fcat/showTaxa.py
fcat-0.1.10.dist-info/licenses/LICENSE
fcat-0.1.10.dist-info/METADATA
fcat-0.1.10.dist-info/WHEEL
fcat-0.1.10.dist-info/entry_points.txt
fcat-0.1.10.dist-info/top_level.txt
fcat-0.1.10.dist-info/RECORD
