Metadata-Version: 2.4
Name: fcat
Version: 0.1.10
Summary: Python package for fCAT, a feature-aware completeness assessment tool
Home-page: https://github.com/BIONF/fCAT
Author: Vinh Tran
Author-email: tran@bio.uni-frankfurt.de
License: GPL-3.0
Classifier: Environment :: Console
Classifier: Intended Audience :: End Users/Desktop
Classifier: License :: OSI Approved :: GNU General Public License v3 or later (GPLv3+)
Classifier: Natural Language :: English
Classifier: Programming Language :: Python :: 3
Requires-Python: >=3.12.0
License-File: LICENSE
Requires-Dist: biopython
Requires-Dist: tqdm
Requires-Dist: ete4
Requires-Dist: six
Requires-Dist: greedyFAS>=1.18.0
Requires-Dist: fdog>=1.0.0
Requires-Dist: rpy2
Requires-Dist: tzlocal
Requires-Dist: scipy
Dynamic: author
Dynamic: author-email
Dynamic: classifier
Dynamic: description
Dynamic: description-content-type
Dynamic: home-page
Dynamic: license
Dynamic: license-file
Dynamic: requires-dist
Dynamic: requires-python
Dynamic: summary
